pipexec/__init__.py
pipexec/cli.py
pipexec-0.2.6.dist-info/entry_points.txt
pipexec-0.2.6.dist-info/LICENSE
pipexec-0.2.6.dist-info/WHEEL
pipexec-0.2.6.dist-info/METADATA
pipexec-0.2.6.dist-info/RECORD
